setup.py
simple_virtuoso_migrate/__init__.py
simple_virtuoso_migrate/cli.py
simple_virtuoso_migrate/config.py
simple_virtuoso_migrate/helpers.py
simple_virtuoso_migrate/log.py
simple_virtuoso_migrate/main.py
simple_virtuoso_migrate/run.py
simple_virtuoso_migrate/ssh.py
simple_virtuoso_migrate/version.py
simple_virtuoso_migrate/virtuoso.py
simple_virtuoso_migrate.egg-info/PKG-INFO
simple_virtuoso_migrate.egg-info/SOURCES.txt
simple_virtuoso_migrate.egg-info/dependency_links.txt
simple_virtuoso_migrate.egg-info/entry_points.txt
simple_virtuoso_migrate.egg-info/requires.txt
simple_virtuoso_migrate.egg-info/top_level.txt
simple_virtuoso_migrate/core/__init__.py
simple_virtuoso_migrate/core/exceptions.py
simple_virtuoso_migrate/virtuoso_migrate/__init__.py
simple_virtuoso_migrate/virtuoso_migrate/management/__init__.py
simple_virtuoso_migrate/virtuoso_migrate/management/commands/__init__.py
simple_virtuoso_migrate/virtuoso_migrate/management/commands/virtuoso_migrate.py
tests/__init__.py
tests/cli_test.py
tests/config_test.py
tests/core_test.py
tests/exceptions_test.py
tests/helpers_test.py
tests/log_test.py
tests/main_test.py
tests/run_test.py
tests/virtuoso_test.py