Metadata-Version: 1.0
Name: simple-virtuoso-migrate
Version: 0.8.3
Summary: simple-virtuoso-migrate is a Virtuoso database migration tool inspired on simple-db-migrate.
Home-page: http://github.com/globocom/simple-virtuoso-migrate/
Author: Percy Rivera
Author-email: priverasalas@gmail.com
License: Apache License 2.0
Keywords: database migration tool virtuoso
Platform: UNKNOWN
